MANIFEST.in
README.md
setup.cfg
setup.py
graphitty/__init__.py
graphitty/combiner.py
graphitty/comparator.py
graphitty/graphitty.py
graphitty.egg-info/PKG-INFO
graphitty.egg-info/SOURCES.txt
graphitty.egg-info/dependency_links.txt
graphitty.egg-info/top_level.txt