Metadata-Version: 1.0
Name: graphitty
Version: 0.0.2
Summary: A Python library that convert time series to direction Graph to discover the story within data.
Home-page: https://github.com/sketchytechky/graphitty
Author: Boris Lau
Author-email: boris@techie.im
License: UNKNOWN
Platform: UNKNOWN
